odoo10_addon_l10n_fr_mis_reports-10.0.1.0.0-py2.7-nspkg.pth
odoo/addons/l10n_fr_mis_reports/README.rst
odoo/addons/l10n_fr_mis_reports/__init__.py
odoo/addons/l10n_fr_mis_reports/__manifest__.py
odoo/addons/l10n_fr_mis_reports/data/mis_report_bs.xml
odoo/addons/l10n_fr_mis_reports/data/mis_report_bs_simplified.xml
odoo/addons/l10n_fr_mis_reports/data/mis_report_pl.xml
odoo/addons/l10n_fr_mis_reports/data/mis_report_pl_simplified.xml
odoo/addons/l10n_fr_mis_reports/data/mis_report_styles.xml
odoo/addons/l10n_fr_mis_reports/i18n/it.po
odoo10_addon_l10n_fr_mis_reports-10.0.1.0.0.dist-info/DESCRIPTION.rst
odoo10_addon_l10n_fr_mis_reports-10.0.1.0.0.dist-info/METADATA
odoo10_addon_l10n_fr_mis_reports-10.0.1.0.0.dist-info/RECORD
odoo10_addon_l10n_fr_mis_reports-10.0.1.0.0.dist-info/WHEEL
odoo10_addon_l10n_fr_mis_reports-10.0.1.0.0.dist-info/metadata.json
odoo10_addon_l10n_fr_mis_reports-10.0.1.0.0.dist-info/namespace_packages.txt
odoo10_addon_l10n_fr_mis_reports-10.0.1.0.0.dist-info/top_level.txt
